byted_growtopia/__init__.py
byted_growtopia-0.0.1.dist-info/METADATA
byted_growtopia-0.0.1.dist-info/WHEEL
byted_growtopia-0.0.1.dist-info/top_level.txt
byted_growtopia-0.0.1.dist-info/RECORD
